odoo/addons/fieldservice_equipment_warranty/README.rst
odoo/addons/fieldservice_equipment_warranty/__init__.py
odoo/addons/fieldservice_equipment_warranty/__manifest__.py
odoo/addons/fieldservice_equipment_warranty/i18n/fieldservice_equipment_warranty.pot
odoo/addons/fieldservice_equipment_warranty/i18n/fr.po
odoo/addons/fieldservice_equipment_warranty/i18n/it.po
odoo/addons/fieldservice_equipment_warranty/models/__init__.py
odoo/addons/fieldservice_equipment_warranty/models/fsm_equipment.py
odoo/addons/fieldservice_equipment_warranty/readme/CONTRIBUTORS.md
odoo/addons/fieldservice_equipment_warranty/readme/DESCRIPTION.md
odoo/addons/fieldservice_equipment_warranty/static/description/icon.png
odoo/addons/fieldservice_equipment_warranty/static/description/index.html
odoo/addons/fieldservice_equipment_warranty/tests/__init__.py
odoo/addons/fieldservice_equipment_warranty/tests/test_fsm_equipment_warranty.py
odoo/addons/fieldservice_equipment_warranty/views/fsm_equipment.xml
odoo_addon_fieldservice_equipment_warranty-18.0.1.0.0.4.dist-info/METADATA
odoo_addon_fieldservice_equipment_warranty-18.0.1.0.0.4.dist-info/WHEEL
odoo_addon_fieldservice_equipment_warranty-18.0.1.0.0.4.dist-info/top_level.txt
odoo_addon_fieldservice_equipment_warranty-18.0.1.0.0.4.dist-info/RECORD
