Metadata-Version: 2.1
Name: odoo-addon-fieldservice_equipment_warranty
Version: 18.0.1.0.0.4
Requires-Python: >=3.10
Requires-Dist: odoo-addon-fieldservice_equipment_stock==18.0.*
Requires-Dist: odoo-addon-product_warranty==18.0.*
Requires-Dist: odoo==18.0.*
Summary: Field Service equipment warranty
Home-page: https://github.com/OCA/field-service
License: AGPL-3
Author: Camptocamp, Odoo Community Association (OCA)
Author-email: support@odoo-community.org
Classifier: Programming Language :: Python
Classifier: Framework :: Odoo
Classifier: Framework :: Odoo :: 18.0
Classifier: License :: OSI Approved :: GNU Affero General Public License v3
